up_bfgp/__init__.py
up_bfgp/bfgp.py
up_bfgp/bfgp_pp/main.bin
up_bfgp/bfgp_pp/preprocess/pddl_translator.py
up_bfgp-0.2.0.dist-info/LICENSE
up_bfgp-0.2.0.dist-info/METADATA
up_bfgp-0.2.0.dist-info/WHEEL
up_bfgp-0.2.0.dist-info/top_level.txt
up_bfgp-0.2.0.dist-info/RECORD
