Metadata-Version: 2.1
Name: up-bfgp
Version: 0.2.0
Summary: Unified Planning integration of the BFGP++ generalized planner
Author: Javier Segovia-Aguas, Sergio Jiménez and Anders Jonsson
Author-email: javier.segovia@upf.edu
License: GNUv3
License-File: LICENSE
